[
	{
		"title": "На места в рамках КЦП (по всем формам обучения)",
		"classname": "col l4 m6 s12",
		"events": [			
			{
				"date": "15 июля",
				"event": "Завершение приёма документов от поступающих на обучение с прохождением ВИ**, проводимых вузом самостоятельно"
			},
			{
				"date": "25 июля",
				"event": "Завершение приёма документов от поступающих на обучение по результатам ЕГЭ, в том числе от поступающих без ВИ"
			},
			{
				"date": "27 июля",
				"event": "Размещение конкурсных списков"
			},
			{
				"date": "28 июля",
				"time": "12:00 по МСК",
				"classname": "selected1",
				"event": "Завершение приёма оригиналов от лиц, подлежащих зачислению на места в пределах особой, отдельной и целевой квот"
			},
			{
				"date": "29-30 июля",
				"event": "Издание приказов о зачислении на этапе приоритетного зачисления на места в пределах особой, отдельной и целевой квот"
			},
			{
				"date": "3 августа",
				"time": "12:00 по МСК",
				"classname": "selected1",
				"event": "Завершение приёма оригиналов от лиц, подлежащих зачислению на основном этапе"
			},
			{
				"date": "4-9 августа",
				"event": "Издание приказов о зачислении на основном этапе"
			}
		]
	},
	{
		"title": "На места по договорам об оказании платных образовательных услуг (по очной форме обучения)",
		"classname": "col l4 m6 s12",
		"events": [
			{
				"date": "5 августа",
				"event": "Завершение приёма документов от поступающих на обучение с прохождением ВИ, проводимых вузом самостоятельно"
			},
			{
				"date": "16 августа",
				"classname": "selected2",
				"event": "Завершение приёма документов от поступающих на обучение по результатам ЕГЭ"
			},
			{
				"date": "17 августа",
				"event": "Размещение конкурсных списков"
			},
			{
				"date": "19 августа",
				"event": "Завершение заключения договоров об оказании платных образовательных услуг"
			},
			{
				"date": "20 августа",
				"event": "Издание приказов о зачислении"
			}
		]
	},
	{
		"title": "На места по договорам об оказании платных образовательных услуг (по заочной и очно-заочной форме обучения)",
		"classname": "col l4 m12",
		"events": [
			{
				"date": "5 августа",
				"event": "Завершение приёма документов от поступающих на обучение с прохождением ВИ, проводимых вузом самостоятельно"
			},
			{
				"date": "20 августа",
				"classname": "selected1",
				"event": "Завершение приёма документов от поступающих на обучение по результатам ЕГЭ, в том числе от поступающих без ВИ"
			},
			{
				"date": "21 августа",
				"event": "Размещение конкурсных списков"
			},
			{
				"date": "22 августа",
				"event": "Завершение заключения договоров об оказании платных образовательных услуг"
			},
			{
				"date": "23 августа",
				"event": "Издание приказов о зачислении"
			}
		]
	}
]